{"Sokenzan Renegade": ["$0.20", "$0.05"], "Kiri-Onna": ["$0.18", "$0.06"], "Yuki-Onna": ["$0.18", "$0.05"], "Undying Flames": ["$0.37", "$0.10"], "One with Nothing": ["$1.89", "$0.50"], "Kataki, War's Wage": ["$6.59", "$1.75"], "Blood Clock": ["$0.46", "$0.19"], "Ghost-Lit Redeemer": ["$0.25", "$0.05"], "Manriki-Gusari": ["$0.84", "$0.27"], "Into the Fray": ["$0.19", "$0.05"], "Descendant of Masumaro": ["$0.20", "$0.06"], "Eternal Dominion": ["$2.99", "$1.31"], "Captive Flame": ["$0.20", "$0.05"], "Spiraling Embers": ["$0.20", "$0.05"], "Ghost-Lit Nourisher": ["$0.18", "$0.05"], "Spiritual Visit": ["$0.23", "$0.05"], "Celestial Kirin": ["$0.37", "$0.25"], "Nikko-Onna": ["$0.25", "$0.06"], "Pain's Reward": ["$0.42", "$0.25"], "Sekki, Seasons' Guide": ["$1.00", "$0.50"], "Gaze of Adamaro": ["$0.20", "$0.06"], "Kagemaro's Clutch": ["$0.19", "$0.05"], "Rending Vines": ["$0.20", "$0.05"], "Molting Skin": ["$0.22", "$0.06"], "Iname as One": ["$0.37", "$0.15"], "Soratami Cloud Chariot": ["$0.23", "$0.06"], "Evermind": ["$0.22", "$0.05"], "Kemuri-Onna": ["$0.18", "$0.05"], "Pithing Needle": ["$4.49", "$3.00"], "Kami of the Crescent Moon": ["$2.47", "$1.00"], "Infernal Kirin": ["$0.45", "$0.15"], "Okina Nightwatch": ["$0.20", "$0.05"], "Death of a Thousand Stings": ["$0.19", "$0.05"], "Tomb of Urami": ["$0.37", "$0.10"], "AEther Shockwave": ["$0.24", "$0.02"], "Hand of Honor": ["$0.94", "$0.25"], "Kuon, Ogre Ascendant": ["$0.99", "$0.25"], "Path of Anger's Flame": ["$0.23", "$0.05"], "Inner Fire": ["$0.20", "$0.08"], "Kiku's Shadow": ["$0.29", "$0.06"], "Mikokoro, Center of the Sea": ["$16.09", "$8.80"], "Descendant of Soramaro": ["$0.19", "$0.05"], "Plow Through Reito": ["$0.20", "$0.05"], "Cloudhoof Kirin": ["$0.32", "$0.10"], "Adamaro, First to Desire": ["$0.56", "$0.25"], "Rune-Tail, Kitsune Ascendant": ["$4.99", "$3.45"], "Ebony Owl Netsuke": ["$0.94", "$0.25"], "O-Naginata": ["$1.00", "$0.50"], "Shinen of Stars' Light": ["$0.20", "$0.05"], "Inner Calm, Outer Strength": ["$0.19", "$0.05"], "Kitsune Loreweaver": ["$0.19", "$0.06"], "Stampeding Serow": ["$0.20", "$0.05"], "Reverence": ["$0.43", "$0.12"], "Shape Stealer": ["$0.18", "$0.15"], "Neverending Torment": ["$0.25", "$0.15"], "Charge Across the Araba": ["$0.21", "$0.06"], "Eiganjo Free-Riders": ["$0.18", "$0.05"], "Torii Watchward": ["$0.20", "$0.05"], "Dense Canopy": ["$0.23", "$0.05"], "Maga, Traitor to Mortals": ["$3.49", "$1.50"], "Reki, the History of Kamigawa": ["$1.00", "$0.80"], "Death Denied": ["$0.20", "$0.06"], "Oboro Breezecaller": ["$0.23", "$0.05"], "Inner-Chamber Guard": ["$0.22", "$0.16"], "Hidetsugu's Second Rite": ["$0.79", "$0.32"], "Matsu-Tribe Birdstalker": ["$0.18", "$0.05"], "Kami of the Tended Garden": ["$0.20", "$0.05"], "Dosan's Oldest Chant": ["$0.19", "$0.05"], "Ashes of the Fallen": ["$0.39", "$0.10"], "Akki Underling": ["$0.19", "$0.05"], "Barrel Down Sokenzan": ["$0.19", "$0.05"], "Moonbow Illusionist": ["$0.19", "$0.05"], "Freed from the Real": ["$0.69", "$0.25"], "Shinen of Life's Roar": ["$0.20", "$0.06"], "Razorjaw Oni": ["$0.20", "$0.05"], "Sakura-Tribe Scout": ["$1.20", "$0.80"], "Akki Drillmaster": ["$0.19", "$0.05"], "Moonwing Moth": ["$0.20", "$0.05"], "Akuta, Born of Ash": ["$0.31", "$0.10"], "Wine of Blood and Iron": ["$0.37", "$0.10"], "Twincast": ["$2.99", "$1.50"], "Choice of Damnations": ["$4.85", "$2.25"], "Seed the Land": ["$0.57", "$0.42"], "Shinen of Flight's Wings": ["$0.20", "$0.05"], "Oni of Wild Places": ["$0.20", "$0.05"], "Oboro Envoy": ["$0.20", "$0.05"], "Kagemaro, First to Suffer": ["$1.49", "$0.50"], "Rushing-Tide Zubera": ["$0.18", "$0.05"], "Descendant of Kiyomaro": ["$0.20", "$0.05"], "Locust Miser": ["$0.75", "$0.33"], "Murmurs from Beyond": ["$0.20", "$0.05"], "Gnat Miser": ["$0.28", "$0.06"], "Hail of Arrows": ["$0.20", "$0.05"], "Arashi, the Sky Asunder": ["$0.79", "$0.25"], "Skyfire Kirin": ["$0.31", "$0.10"], "Measure of Wickedness": ["$0.22", "$0.06"], "Masumaro, First to Live": ["$0.49", "$0.24"], "Ideas Unbound": ["$0.58", "$0.10"], "Ronin Cavekeeper": ["$0.20", "$0.05"], "Dreamcatcher": ["$0.19", "$0.05"], "Thoughts of Ruin": ["$0.37", "$0.10"], "Hand of Cruelty": ["$0.24", "$0.08"], "Secretkeeper": ["$0.20", "$0.05"], "Footsteps of the Goryo": ["$2.07", "$0.60"], "Sunder from Within": ["$0.23", "$0.05"], "Pure Intentions": ["$0.37", "$0.10"], "Promised Kannushi": ["$0.20", "$0.05"], "Haru-Onna": ["$0.22", "$0.05"], "Kaho, Minamo Historian": ["$2.85", "$0.86"], "Sakashima the Impostor": ["$12.97", "$9.00"], "Miren, the Moaning Well": ["$14.93", "$7.00"], "Jiwari, the Earth Aflame": ["$0.29", "$0.10"], "Kashi-Tribe Elite": ["$0.31", "$0.10"], "Trusted Advisor": ["$0.18", "$0.06"], "Enduring Ideal": ["$7.99", "$3.00"], "Briarknit Kami": ["$0.20", "$0.05"], "Endless Swarm": ["$0.37", "$0.28"], "Kuro's Taken": ["$0.20", "$0.05"], "Sokenzan Spellblade": ["$0.20", "$0.05"], "Ayumi, the Last Visitor": ["$0.41", "$0.15"], "Deathmask Nezumi": ["$0.19", "$0.05"], "Shifting Borders": ["$0.25", "$0.07"], "Oboro, Palace in the Clouds": ["$17.09", "$11.00"], "Shinen of Fury's Fire": ["$0.20", "$0.05"], "Seek the Horizon": ["$0.23", "$0.05"], "Minamo Scrollkeeper": ["$0.19", "$0.05"], "Godo's Irregulars": ["$0.20", "$0.05"], "Deathknell Kami": ["$0.19", "$0.05"], "Michiko Konda, Truth Seeker": ["$7.64", "$4.50"], "Ghost-Lit Raider": ["$0.18", "$0.05"], "Burning-Eye Zubera": ["$0.18", "$0.05"], "Oppressive Will": ["$0.20", "$0.05"], "Exile into Darkness": ["$0.20", "$0.05"], "Promise of Bunrei": ["$3.39", "$1.74"], "Raving Oni-Slave": ["$0.18", "$0.05"], "Nightsoil Kami": ["$0.20", "$0.05"], "Sink into Takenuma": ["$0.20", "$0.05"], "Cowed by Wisdom": ["$0.19", "$0.05"], "Homura, Human Ascendant": ["$3.29", "$1.25"], "Bounteous Kirin": ["$0.38", "$0.10"], "Curtain of Light": ["$0.19", "$0.05"], "Elder Pine of Jukai": ["$0.19", "$0.05"], "Cut the Earthly Bond": ["$0.19", "$0.05"], "Ghost-Lit Stalker": ["$0.18", "$0.05"], "Skull Collector": ["$0.24", "$0.06"], "Kitsune Dawnblade": ["$0.19", "$0.05"], "Fiddlehead Kami": ["$0.19", "$0.05"], "Kiyomaro, First to Stand": ["$0.34", "$0.10"], "Shinen of Fear's Chill": ["$0.20", "$0.05"], "Overwhelming Intellect": ["$0.31", "$0.06"], "Scroll of Origins": ["$0.34", "$0.10"], "Kami of Empty Graves": ["$0.19", "$0.05"], "Presence of the Wise": ["$0.20", "$0.05"], "Meishin, the Mind Cage": ["$1.27", "$0.75"], "Iizuka the Ruthless": ["$0.62", "$0.28"], "Araba Mothrider": ["$0.19", "$0.07"], "Kitsune Bonesetter": ["$0.19", "$0.05"], "Feral Lightning": ["$0.22", "$0.05"], "Glitterfang": ["$0.19", "$0.05"], "Sasaya, Orochi Ascendant": ["$0.43", "$0.25"], "Erayo, Soratami Ascendant": ["$8.66", "$4.50"], "Rally the Horde": ["$0.37", "$0.10"], "Ivory Crane Netsuke": ["$0.20", "$0.06"], "Soramaro, First to Dream": ["$0.25", "$0.10"], "Ghost-Lit Warder": ["$0.18", "$0.05"]}