{"Mischievous Quanar": ["$0.38", "$0.10"], "Dawn Elemental": ["$0.76", "$0.22"], "One with Nature": ["$0.26", "$0.06"], "Dragon Tyrant": ["$2.34", "$1.00"], "Faces of the Past": ["$0.34", "$0.10"], "Skirk Volcanist": ["$0.20", "$0.05"], "Goblin War Strike": ["$0.62", "$0.25"], "Zealous Inquisitor": ["$0.17", "$0.05"], "Long-Term Plans": ["$2.19", "$0.75"], "Edgewalker": ["$0.49", "$0.06"], "Reaping the Graves": ["$0.23", "$0.06"], "Mercurial Kite": ["$0.16", "$0.05"], "Claws of Wirewood": ["$0.20", "$0.06"], "Woodcloaker": ["$0.17", "$0.05"], "Siege-Gang Commander": ["$2.63", "$0.75"], "Carbonize": ["$0.20", "$0.05"], "Aven Liberator": ["$0.16", "$0.05"], "Rock Jockey": ["$0.17", "$0.06"], "Enrage": ["$0.22", "$0.06"], "Frontline Strategist": ["$0.16", "$0.05"], "Wipe Clean": ["$0.17", "$0.05"], "Titanic Bulvox": ["$0.17", "$0.05"], "Cabal Interrogator": ["$0.31", "$0.05"], "Sprouting Vines": ["$0.19", "$0.05"], "Shoreline Ranger": ["$0.17", "$0.05"], "Dragon Scales": ["$0.16", "$0.05"], "Raven Guild Master": ["$1.50", "$0.46"], "Brain Freeze": ["$1.06", "$0.72"], "Aven Farseer": ["$0.16", "$0.05"], "Ageless Sentinels": ["$0.33", "$0.10"], "Uncontrolled Infestation": ["$0.17", "$0.06"], "Scornful Egotist": ["$0.15", "$0.05"], "Temple of the False God": ["$0.74", "$0.20"], "Wing Shards": ["$0.27", "$0.05"], "Gilded Light": ["$0.23", "$0.06"], "Pemmin's Aura": ["$0.84", "$0.65"], "Undead Warchief": ["$4.78", "$3.50"], "Daru Spiritualist": ["$0.13", "$0.05"], "Day of the Dragons": ["$0.63", "$0.10"], "Decree of Justice": ["$0.96", "$0.12"], "Pyrostatic Pillar": ["$0.57", "$0.26"], "Daru Warchief": ["$1.45", "$0.50"], "Unburden": ["$0.17", "$0.05"], "Dragonstorm": ["$0.84", "$0.29"], "Coast Watcher": ["$0.16", "$0.05"], "Decree of Pain": ["$3.26", "$2.25"], "Torrent of Fire": ["$0.17", "$0.05"], "Hindering Touch": ["$0.16", "$0.06"], "Temporal Fissure": ["$0.28", "$0.06"], "Raven Guild Initiate": ["$0.19", "$0.06"], "Sliver Overlord": ["$12.97", "$8.00"], "Eternal Dragon": ["$1.06", "$0.24"], "Stifle": ["$5.66", "$2.90"], "Final Punishment": ["$0.33", "$0.10"], "Reward the Faithful": ["$0.23", "$0.05"], "Trap Digger": ["$0.40", "$0.10"], "Tendrils of Agony": ["$1.90", "$1.15"], "Stabilizer": ["$0.37", "$0.10"], "Dragonstalker": ["$0.20", "$0.06"], "Parallel Thoughts": ["$0.39", "$0.16"], "Dragon Shadow": ["$0.16", "$0.06"], "Death's-Head Buzzard": ["$0.13", "$0.05"], "Scattershot": ["$0.17", "$0.06"], "Recuperate": ["$0.17", "$0.05"], "Goblin Warchief": ["$1.54", "$0.75"], "Bladewing the Risen": ["$2.77", "$1.70"], "Decree of Annihilation": ["$1.46", "$0.50"], "Fatal Mutation": ["$0.20", "$0.05"], "Wirewood Symbiote": ["$1.29", "$0.69"], "Putrid Raptor": ["$0.22", "$0.06"], "Chill Haunting": ["$0.20", "$0.05"], "Break Asunder": ["$0.16", "$0.05"], "Bladewing's Thrall": ["$0.22", "$0.05"], "Exiled Doomsayer": ["$0.33", "$0.10"], "Decree of Silence": ["$0.89", "$0.22"], "Extra Arms": ["$0.22", "$0.05"], "Krosan Warchief": ["$0.27", "$0.05"], "Cabal Conditioning": ["$0.33", "$0.10"], "Spark Spray": ["$0.20", "$0.05"], "Force Bubble": ["$0.31", "$0.10"], "Clutch of Undeath": ["$0.16", "$0.05"], "Treetop Scout": ["$0.20", "$0.05"], "Metamorphose": ["$0.24", "$0.06"], "Mistform Warchief": ["$0.25", "$0.06"], "Guilty Conscience": ["$0.22", "$0.06"], "Frozen Solid": ["$0.16", "$0.05"], "Xantid Swarm": ["$2.13", "$0.38"], "Carrion Feeder": ["$0.47", "$0.10"], "Zombie Cutthroat": ["$0.17", "$0.05"], "Kurgadon": ["$0.21", "$0.05"], "Sulfuric Vortex": ["$1.50", "$0.35"], "Silver Knight": ["$0.33", "$0.05"], "Aphetto Runecaster": ["$0.20", "$0.05"], "Ark of Blight": ["$0.20", "$0.06"], "Twisted Abomination": ["$0.17", "$0.05"], "Vengeful Dead": ["$0.23", "$0.10"], "Hunting Pack": ["$0.20", "$0.05"], "Root Elemental": ["$0.32", "$0.10"], "Ancient Ooze": ["$0.44", "$0.15"], "Lingering Death": ["$0.16", "$0.05"], "Unspeakable Symbol": ["$0.62", "$0.25"], "Misguided Rage": ["$0.16", "$0.05"], "Proteus Machine": ["$0.21", "$0.06"], "Consumptive Goo": ["$0.37", "$0.10"], "Accelerated Mutation": ["$0.16", "$0.05"], "Rain of Blades": ["$0.20", "$0.05"], "Dragon Wings": ["$0.19", "$0.05"], "Lethal Vapors": ["$0.74", "$0.25"], "Ambush Commander": ["$1.81", "$0.50"], "Karona's Zealot": ["$0.20", "$0.05"], "Call to the Grave": ["$0.65", "$0.28"], "Thundercloud Elemental": ["$0.20", "$0.05"], "Fierce Empath": ["$0.91", "$0.33"], "Noble Templar": ["$0.16", "$0.05"], "Form of the Dragon": ["$0.40", "$0.10"], "Goblin Psychopath": ["$0.20", "$0.05"], "Karona, False God": ["$0.82", "$0.40"], "Chartooth Cougar": ["$0.16", "$0.05"], "Soul Collector": ["$0.45", "$0.20"], "Dragon Breath": ["$0.27", "$0.06"], "Alpha Status": ["$0.98", "$0.52"], "Mind's Desire": ["$2.32", "$0.95"], "Bonethorn Valesk": ["$0.16", "$0.05"], "Krosan Drover": ["$0.21", "$0.05"], "Primitive Etchings": ["$0.38", "$0.14"], "Rush of Knowledge": ["$0.17", "$0.05"], "Riptide Survivor": ["$0.26", "$0.05"], "Dispersal Shield": ["$0.18", "$0.05"], "Decree of Savagery": ["$0.44", "$0.15"], "Grip of Chaos": ["$0.79", "$0.52"], "Astral Steel": ["$0.16", "$0.05"], "Goblin Brigand": ["$0.16", "$0.05"], "Dragonspeaker Shaman": ["$3.07", "$1.70"], "Dimensional Breach": ["$0.35", "$0.10"], "Elvish Aberration": ["$0.25", "$0.06"], "Skulltap": ["$0.17", "$0.06"], "Nefashu": ["$0.35", "$0.10"], "Dragon Mage": ["$2.16", "$0.50"], "Upwelling": ["$0.46", "$0.10"], "Forgotten Ancient": ["$1.24", "$0.25"], "Divergent Growth": ["$0.16", "$0.05"], "Wirewood Guardian": ["$0.19", "$0.05"], "Dragon Fangs": ["$0.18", "$0.06"]}