{"Dizzying Gaze": ["$0.19", "$0.05"], "Thrull Surgeon": ["$0.25", "$0.05"], "Oath of Lieges": ["$2.24", "$0.75"], "Treasure Hunter": ["$0.18", "$0.05"], "Dauthi Cutthroat": ["$0.32", "$0.06"], "Mirri, Cat Warrior": ["$0.67", "$0.33"], "City of Traitors": ["$145.70", "$90.00"], "Spellbook": ["$0.63", "$0.18"], "Coat of Arms": ["$11.05", "$6.00"], "Bequeathal": ["$0.21", "$0.05"], "Cartographer": ["$0.20", "$0.05"], "Survival of the Fittest": ["$45.76", "$30.00"], "Spike Rogue": ["$0.25", "$0.05"], "Elvish Berserker": ["$0.17", "$0.05"], "Wayward Soul": ["$0.18", "$0.05"], "Fighting Chance": ["$0.31", "$0.10"], "Scare Tactics": ["$0.20", "$0.05"], "Pandemonium": ["$1.47", "$0.50"], "Penance": ["$0.27", "$0.06"], "Mage il-Vec": ["$0.17", "$0.05"], "Hatred": ["$9.96", "$3.80"], "Welkin Hawk": ["$0.19", "$0.05"], "Plaguebearer": ["$0.91", "$0.52"], "Exalted Dragon": ["$0.49", "$0.10"], "Plated Rootwalla": ["$0.17", "$0.05"], "Jackalope Herd": ["$0.17", "$0.05"], "Merfolk Looter": ["$0.21", "$0.05"], "Grollub": ["$0.17", "$0.05"], "Price of Progress": ["$2.19", "$1.00"], "School of Piranha": ["$0.20", "$0.05"], "Keeper of the Light": ["$0.22", "$0.05"], "Robe of Mirrors": ["$0.17", "$0.05"], "Sabertooth Wyvern": ["$0.23", "$0.05"], "Nausea": ["$0.18", "$0.05"], "Erratic Portal": ["$1.39", "$0.72"], "Wall of Nets": ["$1.00", "$0.45"], "Pegasus Stampede": ["$0.22", "$0.05"], "Oath of Druids": ["$5.56", "$3.00"], "Keeper of the Dead": ["$0.18", "$0.11"], "Scalding Salamander": ["$0.20", "$0.05"], "Wood Elves": ["$0.32", "$0.06"], "Rootwater Mystic": ["$0.17", "$0.05"], "Spike Cannibal": ["$0.43", "$0.08"], "Rootwater Alligator": ["$0.17", "$0.05"], "Culling the Weak": ["$0.95", "$0.25"], "Memory Crystal": ["$0.66", "$0.24"], "Song of Serenity": ["$0.23", "$0.05"], "Mind Maggots": ["$0.24", "$0.06"], "Curiosity": ["$0.42", "$0.08"], "Mogg Assassin": ["$0.36", "$0.21"], "Zealots en-Dal": ["$0.18", "$0.06"], "Transmogrifying Licid": ["$0.25", "$0.05"], "Kor Chant": ["$0.16", "$0.05"], "Cinder Crawler": ["$0.19", "$0.05"], "Shield Mate": ["$0.20", "$0.05"], "Volrath's Dungeon": ["$0.25", "$0.10"], "Reconnaissance": ["$1.99", "$0.60"], "Limited Resources": ["$0.66", "$0.15"], "Reclaim": ["$0.19", "$0.06"], "Thalakos Drifters": ["$0.22", "$0.10"], "Keeper of the Mind": ["$0.22", "$0.11"], "Cursed Flesh": ["$0.19", "$0.05"], "Dauthi Warlord": ["$0.30", "$0.05"], "Resuscitate": ["$0.21", "$0.06"], "Skyshroud Elite": ["$0.35", "$0.05"], "Keeper of the Flame": ["$0.18", "$0.05"], "Paladin en-Vec": ["$0.68", "$0.10"], "Standing Troops": ["$0.20", "$0.05"], "Vampire Hounds": ["$0.25", "$0.05"], "Equilibrium": ["$1.99", "$0.50"], "Workhorse": ["$0.00", "$0.22"], "Carnophage": ["$0.29", "$0.05"], "Treasure Trove": ["$0.18", "$0.05"], "Scrivener": ["$0.23", "$0.06"], "Necrologia": ["$0.23", "$0.08"], "Cataclysm": ["$7.53", "$2.85"], "Pit Spawn": ["$0.44", "$0.25"], "Killer Whale": ["$0.18", "$0.06"], "Monstrous Hound": ["$0.27", "$0.10"], "Oath of Scholars": ["$0.31", "$0.10"], "Theft of Dreams": ["$0.18", "$0.05"], "Shattering Pulse": ["$0.32", "$0.05"], "High Ground": ["$0.27", "$0.05"], "Avenging Druid": ["$0.19", "$0.05"], "Paroxysm": ["$0.18", "$0.05"], "Mana Breach": ["$0.23", "$0.05"], "Predatory Hunger": ["$0.18", "$0.06"], "Mindless Automaton": ["$0.34", "$0.10"], "Peace of Mind": ["$0.22", "$0.05"], "Forbid": ["$1.94", "$1.00"], "Onslaught": ["$0.19", "$0.05"], "Convalescence": ["$0.34", "$0.10"], "Null Brooch": ["$0.66", "$0.17"], "Rabid Wolverines": ["$0.17", "$0.05"], "Recurring Nightmare": ["$16.08", "$8.00"], "Allay": ["$0.19", "$0.05"], "Cunning": ["$0.19", "$0.05"], "Death's Duet": ["$0.21", "$0.05"], "Thopter Squadron": ["$0.53", "$0.10"], "Shackles": ["$0.20", "$0.05"], "Ravenous Baboons": ["$0.86", "$0.24"], "Skyshroud War Beast": ["$0.54", "$0.10"], "Seismic Assault": ["$1.95", "$0.94"], "Medicine Bag": ["$0.20", "$0.05"], "Spike Hatcher": ["$0.48", "$0.10"], "Keeper of the Beasts": ["$0.21", "$0.05"], "Dauthi Jackal": ["$0.19", "$0.05"], "Reckless Ogre": ["$0.17", "$0.05"], "Soul Warden": ["$1.45", "$0.60"], "Charging Paladin": ["$0.19", "$0.05"], "Flowstone Flood": ["$0.18", "$0.05"], "Fade Away": ["$0.37", "$0.05"], "AEther Tide": ["$0.17", "$0.00"], "Maniacal Rage": ["$0.16", "$0.05"], "Sonic Burst": ["$0.20", "$0.05"], "Slaughter": ["$0.30", "$0.05"], "Dominating Licid": ["$1.16", "$0.28"], "Raging Goblin": ["$0.19", "$0.06"], "Mirozel": ["$0.20", "$0.05"], "Pygmy Troll": ["$0.17", "$0.05"], "Crashing Boars": ["$0.21", "$0.05"], "Thalakos Scout": ["$0.18", "$0.05"], "Cat Burglar": ["$0.19", "$0.05"], "Oath of Ghouls": ["$0.87", "$0.21"], "Manabond": ["$5.18", "$2.36"], "Ertai, Wizard Adept": ["$5.65", "$4.00"], "Spike Weaver": ["$9.00", "$6.70"], "Angelic Blessing": ["$0.19", "$0.06"], "Whiptongue Frog": ["$0.18", "$0.05"], "Spellshock": ["$0.26", "$0.07"], "Soltari Visionary": ["$0.25", "$0.06"], "Mind Over Matter": ["$19.03", "$8.00"], "Furnace Brood": ["$0.17", "$0.05"], "Anarchist": ["$0.19", "$0.06"], "Elven Palisade": ["$0.18", "$0.05"], "Ephemeron": ["$0.27", "$0.10"], "Sphere of Resistance": ["$17.47", "$11.00"], "Entropic Specter": ["$0.27", "$0.10"], "Ogre Shaman": ["$0.30", "$0.10"], "Oath of Mages": ["$0.30", "$0.10"], "Skyshaper": ["$0.26", "$0.05"], "Fugue": ["$0.22", "$0.05"], "Reaping the Rewards": ["$0.17", "$0.05"]}