{"Mystical Tutor": ["$15.63", "$8.00"], "Trinisphere": ["$14.11", "$7.00"], "Strip Mine": ["$29.48", "$18.00"], "Sensei's Divining Top": ["$43.40", "$26.00"], "Necropotence": ["$14.82", "$10.00"], "Tinker": ["$8.90", "$6.50"], "Kird Ape": ["$4.78", "$3.00"], "Serendib Efreet": ["$2.56", "$0.50"], "Goblin Lackey": ["$17.59", "$10.50"], "Gifts Ungiven": ["$15.78", "$10.00"], "Lotus Petal": ["$39.76", "$23.00"], "Balance": ["$7.58", "$4.00"], "Skullclamp": ["$10.19", "$6.00"], "Berserk": ["$52.91", "$18.00"], "Channel": ["$7.71", "$4.20"]}